plug_in/plugin1/__init__.py
plug_in/plugin1/constants.py
plug_in_plugin1-1.0.4.dist-info/METADATA
plug_in_plugin1-1.0.4.dist-info/WHEEL
plug_in_plugin1-1.0.4.dist-info/top_level.txt
plug_in_plugin1-1.0.4.dist-info/RECORD
