Metadata-Version: 2.1
Name: plug-in-plugin1
Version: 1.0.4
Summary: Plugin 1
License: Plug-in Software License Agreement
